[{"text": "failure", "polygon": {"x0": 157, "y0": 151, "x1": 388, "y1": 145, "x2": 450, "y2": 231, "x3": 139, "y3": 293}, "line_idx": 0, "type": "H"}, {"text": "is", "polygon": {"x0": 547, "y0": 184, "x1": 611, "y1": 177, "x2": 625, "y2": 228, "x3": 553, "y3": 231}, "line_idx": 0, "type": "H"}, {"text": "not", "polygon": {"x0": 712, "y0": 179, "x1": 843, "y1": 172, "x2": 853, "y2": 219, "x3": 711, "y3": 226}, "line_idx": 0, "type": "H"}, {"text": "the", "polygon": {"x0": 940, "y0": 171, "x1": 1057, "y1": 176, "x2": 1078, "y2": 219, "x3": 945, "y3": 223}, "line_idx": 0, "type": "H"}, {"text": "opposite", "polygon": {"x0": 1155, "y0": 163, "x1": 1435, "y1": 160, "x2": 1453, "y2": 202, "x3": 1143, "y3": 251}, "line_idx": 0, "type": "H"}, {"text": "of", "polygon": {"x0": 141, "y0": 358, "x1": 240, "y1": 347, "x2": 223, "y2": 433, "x3": 158, "y3": 430}, "line_idx": 1, "type": "H"}, {"text": "success", "polygon": {"x0": 267, "y0": 350, "x1": 527, "y1": 344, "x2": 545, "y2": 387, "x3": 277, "y3": 392}, "line_idx": 1, "type": "H"}, {"text": "it's", "polygon": {"x0": 641, "y0": 343, "x1": 747, "y1": 331, "x2": 758, "y2": 389, "x3": 650, "y3": 392}, "line_idx": 1, "type": "H"}, {"text": "part", "polygon": {"x0": 816, "y0": 343, "x1": 990, "y1": 336, "x2": 983, "y2": 370, "x3": 824, "y3": 411}, "line_idx": 1, "type": "H"}, {"text": "of", "polygon": {"x0": 1037, "y0": 334, "x1": 1146, "y1": 340, "x2": 1116, "y2": 404, "x3": 1043, "y3": 374}, "line_idx": 1, "type": "H"}, {"text": "success", "polygon": {"x0": 1159, "y0": 333, "x1": 1406, "y1": 322, "x2": 1413, "y2": 366, "x3": 1165, "y3": 378}, "line_idx": 1, "type": "H"}, {"text": "Anianna", "polygon": {"x0": 237, "y0": 652, "x1": 514, "y1": 660, "x2": 530, "y2": 710, "x3": 233, "y3": 711}, "line_idx": 2, "type": "H"}, {"text": "Huffington", "polygon": {"x0": 600, "y0": 651, "x1": 956, "y1": 654, "x2": 951, "y2": 740, "x3": 603, "y3": 708}, "line_idx": 2, "type": "H"}]