[{"text": "Lagos", "polygon": {"x0": 238, "y0": 11, "x1": 715, "y1": 31, "x2": 720, "y2": 200, "x3": 263, "y3": 195}, "line_idx": 0, "type": "H"}, {"text": "State", "polygon": {"x0": 851, "y0": 26, "x1": 1297, "y1": 31, "x2": 1309, "y2": 156, "x3": 858, "y3": 171}, "line_idx": 0, "type": "H"}, {"text": "of", "polygon": {"x0": 1353, "y0": 51, "x1": 1535, "y1": 44, "x2": 1529, "y2": 226, "x3": 1372, "y3": 214}, "line_idx": 0, "type": "H"}, {"text": "Nigeria", "polygon": {"x0": 1534, "y0": 2, "x1": 2152, "y1": 0, "x2": 2164, "y2": 224, "x3": 1544, "y3": 258}, "line_idx": 0, "type": "H"}, {"text": "Magistrates'", "polygon": {"x0": 546, "y0": 231, "x1": 1616, "y1": 185, "x2": 1594, "y2": 427, "x3": 564, "y3": 463}, "line_idx": 1, "type": "H"}, {"text": "Court", "polygon": {"x0": 1700, "y0": 211, "x1": 2211, "y1": 255, "x2": 2211, "y2": 400, "x3": 1690, "y3": 389}, "line_idx": 1, "type": "H"}, {"text": "Law", "polygon": {"x0": 2222, "y0": 203, "x1": 2601, "y1": 241, "x2": 2601, "y2": 410, "x3": 2250, "y3": 404}, "line_idx": 1, "type": "H"}, {"text": "and", "polygon": {"x0": 2688, "y0": 286, "x1": 3106, "y1": 159, "x2": 3087, "y2": 379, "x3": 2671, "y3": 378}, "line_idx": 1, "type": "H"}, {"text": "rules", "polygon": {"x0": 337, "y0": 441, "x1": 846, "y1": 432, "x2": 846, "y2": 589, "x3": 341, "y3": 636}, "line_idx": 2, "type": "H"}, {"text": "2009", "polygon": {"x0": 935, "y0": 469, "x1": 1364, "y1": 462, "x2": 1366, "y2": 643, "x3": 937, "y3": 609}, "line_idx": 2, "type": "H"}, {"text": "&", "polygon": {"x0": 1453, "y0": 460, "x1": 1560, "y1": 464, "x2": 1560, "y2": 638, "x3": 1439, "y3": 638}, "line_idx": 2, "type": "H"}, {"text": "2010.", "polygon": {"x0": 1635, "y0": 436, "x1": 2217, "y1": 422, "x2": 2192, "y2": 599, "x3": 1621, "y3": 615}, "line_idx": 2, "type": "H"}, {"text": "1.", "polygon": {"x0": 468, "y0": 1044, "x1": 574, "y1": 1028, "x2": 605, "y2": 1161, "x3": 495, "y3": 1182}, "line_idx": 3, "type": "H"}, {"text": "Civil", "polygon": {"x0": 725, "y0": 918, "x1": 1175, "y1": 937, "x2": 1188, "y2": 1167, "x3": 715, "y3": 1165}, "line_idx": 3, "type": "H"}, {"text": "procedure", "polygon": {"x0": 1338, "y0": 988, "x1": 2339, "y1": 837, "x2": 2398, "y2": 1049, "x3": 1367, "y3": 1211}, "line_idx": 3, "type": "H"}, {"text": "Rules-", "polygon": {"x0": 2464, "y0": 871, "x1": 3163, "y1": 807, "x2": 3215, "y2": 1042, "x3": 2444, "y3": 1077}, "line_idx": 3, "type": "H"}, {"text": "Lagos", "polygon": {"x0": 888, "y0": 1246, "x1": 913, "y1": 1569, "x2": 1528, "y2": 1472, "x3": 1544, "y3": 1287}, "line_idx": 4, "type": "H"}, {"text": "State", "polygon": {"x0": 1685, "y0": 1187, "x1": 2332, "y1": 1158, "x2": 2332, "y2": 1362, "x3": 1663, "y3": 1397}, "line_idx": 4, "type": "H"}, {"text": ".", "polygon": {"x0": 2438, "y0": 1269, "x1": 2488, "y1": 1269, "x2": 2479, "y2": 1300, "x3": 2438, "y3": 1300}, "line_idx": 4, "type": "H"}]