[{"text": "FBS", "polygon": {"x0": 392, "y0": 441, "x1": 527, "y1": 477, "x2": 524, "y2": 533, "x3": 404, "y3": 536}, "line_idx": 0, "type": "H"}, {"text": "%math%", "polygon": {"x0": 616, "y0": 489, "x1": 781, "y1": 489, "x2": 804, "y2": 561, "x3": 622, "y3": 581}, "line_idx": 0, "type": "H"}, {"text": "OR", "polygon": {"x0": 286, "y0": 561, "x1": 395, "y1": 561, "x2": 395, "y2": 623, "x3": 292, "y3": 631}, "line_idx": 1, "type": "H"}, {"text": "PPBS", "polygon": {"x0": 406, "y0": 637, "x1": 555, "y1": 657, "x2": 560, "y2": 701, "x3": 418, "y3": 724}, "line_idx": 1, "type": "H"}, {"text": "200", "polygon": {"x0": 768, "y0": 671, "x1": 885, "y1": 676, "x2": 879, "y2": 724, "x3": 745, "y3": 732}, "line_idx": 1, "type": "H"}, {"text": "OR", "polygon": {"x0": 300, "y0": 732, "x1": 384, "y1": 738, "x2": 395, "y2": 796, "x3": 280, "y3": 805}, "line_idx": 2, "type": "H"}, {"text": "HbA1C", "polygon": {"x0": 432, "y0": 816, "x1": 586, "y1": 838, "x2": 605, "y2": 880, "x3": 420, "y3": 880}, "line_idx": 2, "type": "H"}, {"text": "%math%", "polygon": {"x0": 664, "y0": 838, "x1": 740, "y1": 869, "x2": 742, "y2": 925, "x3": 672, "y3": 908}, "line_idx": 2, "type": "H"}, {"text": "%math%", "polygon": {"x0": 667, "y0": 671, "x1": 737, "y1": 690, "x2": 737, "y2": 741, "x3": 681, "y3": 749}, "line_idx": 1, "type": "H"}, {"text": "6.5", "polygon": {"x0": 779, "y0": 833, "x1": 905, "y1": 841, "x2": 877, "y2": 886, "x3": 776, "y3": 908}, "line_idx": 2, "type": "H"}, {"text": "ADA", "polygon": {"x0": 1772, "y0": 371, "x1": 1921, "y1": 349, "x2": 1929, "y2": 430, "x3": 1750, "y3": 444}, "line_idx": 0, "type": "H"}, {"text": "american", "polygon": {"x0": 1593, "y0": 503, "x1": 1823, "y1": 494, "x2": 1834, "y2": 533, "x3": 1596, "y3": 542}, "line_idx": 1, "type": "H"}, {"text": "diabetology", "polygon": {"x0": 1904, "y0": 461, "x1": 2231, "y1": 466, "x2": 2240, "y2": 547, "x3": 1893, "y3": 539}, "line_idx": 1, "type": "H"}, {"text": "Pt", "polygon": {"x0": 1467, "y0": 746, "x1": 1534, "y1": 749, "x2": 1529, "y2": 808, "x3": 1470, "y3": 827}, "line_idx": 2, "type": "H"}, {"text": "is", "polygon": {"x0": 1638, "y0": 741, "x1": 1708, "y1": 757, "x2": 1702, "y2": 813, "x3": 1663, "y3": 819}, "line_idx": 2, "type": "H"}, {"text": "DIABETIC", "polygon": {"x0": 1772, "y0": 741, "x1": 2066, "y1": 732, "x2": 2083, "y2": 785, "x3": 1775, "y3": 816}, "line_idx": 2, "type": "H"}, {"text": "Association", "polygon": {"x0": 2368, "y0": 424, "x1": 2615, "y1": 433, "x2": 2646, "y2": 491, "x3": 2335, "y3": 528}, "line_idx": 1, "type": "H"}, {"text": "OR", "polygon": {"x0": 322, "y0": 939, "x1": 392, "y1": 934, "x2": 426, "y2": 1004, "x3": 322, "y3": 1023}, "line_idx": 3, "type": "H"}, {"text": "RBS", "polygon": {"x0": 434, "y0": 998, "x1": 549, "y1": 1023, "x2": 558, "y2": 1060, "x3": 448, "y3": 1079}, "line_idx": 3, "type": "H"}, {"text": "%math%", "polygon": {"x0": 622, "y0": 1020, "x1": 684, "y1": 1032, "x2": 684, "y2": 1062, "x3": 628, "y3": 1082}, "line_idx": 3, "type": "H"}, {"text": "200", "polygon": {"x0": 717, "y0": 1012, "x1": 821, "y1": 1026, "x2": 821, "y2": 1057, "x3": 714, "y3": 1062}, "line_idx": 3, "type": "H"}, {"text": "symptoms\"", "polygon": {"x0": 924, "y0": 1009, "x1": 1193, "y1": 1012, "x2": 1213, "y2": 1060, "x3": 927, "y3": 1107}, "line_idx": 3, "type": "H"}, {"text": "HbA1C", "polygon": {"x0": 269, "y0": 1244, "x1": 443, "y1": 1269, "x2": 457, "y2": 1314, "x3": 278, "y3": 1325}, "line_idx": 4, "type": "H"}, {"text": "6", "polygon": {"x0": 376, "y0": 1418, "x1": 398, "y1": 1426, "x2": 404, "y2": 1463, "x3": 373, "y3": 1465}, "line_idx": 5, "type": "H"}, {"text": "to", "polygon": {"x0": 429, "y0": 1415, "x1": 476, "y1": 1432, "x2": 485, "y2": 1468, "x3": 426, "y3": 1477}, "line_idx": 5, "type": "H"}, {"text": "8", "polygon": {"x0": 583, "y0": 1412, "x1": 619, "y1": 1421, "x2": 608, "y2": 1471, "x3": 577, "y3": 1477}, "line_idx": 5, "type": "H"}, {"text": "wks", "polygon": {"x0": 678, "y0": 1412, "x1": 773, "y1": 1418, "x2": 787, "y2": 1465, "x3": 678, "y3": 1468}, "line_idx": 5, "type": "H"}, {"text": "control", "polygon": {"x0": 865, "y0": 1421, "x1": 1025, "y1": 1409, "x2": 1017, "y2": 1460, "x3": 863, "y3": 1474}, "line_idx": 5, "type": "H"}, {"text": "Best", "polygon": {"x0": 334, "y0": 1541, "x1": 437, "y1": 1547, "x2": 432, "y2": 1591, "x3": 328, "y3": 1605}, "line_idx": 6, "type": "H"}, {"text": "Sn", "polygon": {"x0": 558, "y0": 1530, "x1": 642, "y1": 1538, "x2": 667, "y2": 1586, "x3": 555, "y3": 1591}, "line_idx": 6, "type": "H"}, {"text": "a", "polygon": {"x0": 731, "y0": 1544, "x1": 776, "y1": 1552, "x2": 787, "y2": 1591, "x3": 742, "y3": 1597}, "line_idx": 6, "type": "H"}, {"text": "Sp", "polygon": {"x0": 868, "y0": 1538, "x1": 947, "y1": 1552, "x2": 935, "y2": 1619, "x3": 871, "y3": 1608}, "line_idx": 6, "type": "H"}, {"text": "for", "polygon": {"x0": 1084, "y0": 1535, "x1": 1168, "y1": 1552, "x2": 1168, "y2": 1583, "x3": 1095, "y3": 1619}, "line_idx": 6, "type": "H"}, {"text": "IGT", "polygon": {"x0": 1221, "y0": 1530, "x1": 1352, "y1": 1533, "x2": 1352, "y2": 1583, "x3": 1227, "y3": 1594}, "line_idx": 6, "type": "H"}, {"text": "JIPMER", "polygon": {"x0": 1532, "y0": 1488, "x1": 1739, "y1": 1502, "x2": 1750, "y2": 1549, "x3": 1534, "y3": 1541}, "line_idx": 6, "type": "H"}, {"text": "Q", "polygon": {"x0": 1434, "y0": 1488, "x1": 1484, "y1": 1491, "x2": 1473, "y2": 1547, "x3": 1422, "y3": 1547}, "line_idx": 6, "type": "H"}, {"text": "5.7", "polygon": {"x0": 1171, "y0": 1642, "x1": 1271, "y1": 1630, "x2": 1280, "y2": 1686, "x3": 1168, "y3": 1692}, "line_idx": 7, "type": "H"}, {"text": "6.4%", "polygon": {"x0": 1355, "y0": 1628, "x1": 1526, "y1": 1625, "x2": 1532, "y2": 1684, "x3": 1355, "y3": 1703}, "line_idx": 7, "type": "H"}, {"text": "Pitfalls", "polygon": {"x0": 440, "y0": 1728, "x1": 661, "y1": 1728, "x2": 664, "y2": 1832, "x3": 437, "y3": 1852}, "line_idx": 8, "type": "H"}, {"text": "low", "polygon": {"x0": 910, "y0": 1768, "x1": 1003, "y1": 1796, "x2": 1019, "y2": 1835, "x3": 913, "y3": 1843}, "line_idx": 8, "type": "H"}, {"text": "on", "polygon": {"x0": 1165, "y0": 1787, "x1": 1215, "y1": 1790, "x2": 1229, "y2": 1838, "x3": 1168, "y3": 1840}, "line_idx": 8, "type": "H"}, {"text": "in", "polygon": {"x0": 1467, "y0": 1770, "x1": 1529, "y1": 1784, "x2": 1554, "y2": 1815, "x3": 1476, "y3": 1840}, "line_idx": 8, "type": "H"}, {"text": "Anemia", "polygon": {"x0": 786, "y0": 1914, "x1": 963, "y1": 1939, "x2": 977, "y2": 1985, "x3": 771, "y3": 2005}, "line_idx": 9, "type": "H"}, {"text": "Falsely", "polygon": {"x0": 1280, "y0": 1912, "x1": 1444, "y1": 1914, "x2": 1452, "y2": 2003, "x3": 1282, "y3": 2000}, "line_idx": 9, "type": "H"}, {"text": "low", "polygon": {"x0": 1557, "y0": 1927, "x1": 1636, "y1": 1944, "x2": 1636, "y2": 1985, "x3": 1560, "y3": 2010}, "line_idx": 9, "type": "H"}, {"text": "%NA%", "polygon": {"x0": 803, "y0": 2059, "x1": 1009, "y1": 2052, "x2": 1034, "y2": 2098, "x3": 788, "y3": 2108}, "line_idx": 10, "type": "H"}, {"text": "CKD", "polygon": {"x0": 1164, "y0": 2061, "x1": 1277, "y1": 2062, "x2": 1269, "y2": 2112, "x3": 1168, "y3": 2113}, "line_idx": 10, "type": "H"}, {"text": "Thalassemia", "polygon": {"x0": 735, "y0": 2121, "x1": 1086, "y1": 2124, "x2": 1097, "y2": 2230, "x3": 744, "y3": 2244}, "line_idx": 11, "type": "H"}, {"text": "Hereditary", "polygon": {"x0": 768, "y0": 2314, "x1": 1079, "y1": 2315, "x2": 1074, "y2": 2424, "x3": 772, "y3": 2420}, "line_idx": 12, "type": "H"}, {"text": "persistence", "polygon": {"x0": 1118, "y0": 2300, "x1": 1373, "y1": 2301, "x2": 1402, "y2": 2371, "x3": 1118, "y3": 2420}, "line_idx": 12, "type": "H"}, {"text": "of", "polygon": {"x0": 1477, "y0": 2313, "x1": 1542, "y1": 2315, "x2": 1554, "y2": 2434, "x3": 1480, "y3": 2434}, "line_idx": 12, "type": "H"}, {"text": "fetal", "polygon": {"x0": 1589, "y0": 2262, "x1": 1691, "y1": 2267, "x2": 1731, "y2": 2372, "x3": 1589, "y3": 2396}, "line_idx": 12, "type": "H"}, {"text": "Hb", "polygon": {"x0": 1752, "y0": 2310, "x1": 1807, "y1": 2318, "x2": 1836, "y2": 2362, "x3": 1756, "y3": 2378}, "line_idx": 12, "type": "H"}, {"text": "high", "polygon": {"x0": 2279, "y0": 2303, "x1": 2430, "y1": 2305, "x2": 2442, "y2": 2465, "x3": 2290, "y3": 2457}, "line_idx": 12, "type": "H"}, {"text": "Type", "polygon": {"x0": 743, "y0": 2569, "x1": 907, "y1": 2577, "x2": 892, "y2": 2667, "x3": 745, "y3": 2665}, "line_idx": 13, "type": "H"}, {"text": "1.5", "polygon": {"x0": 959, "y0": 2569, "x1": 1055, "y1": 2577, "x2": 1050, "y2": 2618, "x3": 956, "y3": 2628}, "line_idx": 13, "type": "H"}, {"text": "diabetes", "polygon": {"x0": 1136, "y0": 2567, "x1": 1320, "y1": 2569, "x2": 1337, "y2": 2621, "x3": 1131, "y3": 2628}, "line_idx": 13, "type": "H"}, {"text": "15", "polygon": {"x0": 324, "y0": 2815, "x1": 398, "y1": 2823, "x2": 398, "y2": 2858, "x3": 324, "y3": 2880}, "line_idx": 14, "type": "H"}, {"text": "25", "polygon": {"x0": 477, "y0": 2815, "x1": 565, "y1": 2823, "x2": 554, "y2": 2863, "x3": 457, "y3": 2863}, "line_idx": 14, "type": "H"}, {"text": "yr", "polygon": {"x0": 608, "y0": 2841, "x1": 685, "y1": 2841, "x2": 696, "y2": 2904, "x3": 617, "y3": 2922}, "line_idx": 14, "type": "H"}, {"text": "D.K.A", "polygon": {"x0": 1451, "y0": 2795, "x1": 1661, "y1": 2791, "x2": 1687, "y2": 2856, "x3": 1460, "y3": 2854}, "line_idx": 14, "type": "H"}, {"text": "tnt", "polygon": {"x0": 1087, "y0": 2808, "x1": 1173, "y1": 2813, "x2": 1170, "y2": 2859, "x3": 1094, "y3": 2864}, "line_idx": 14, "type": "H"}, {"text": "%NA%", "polygon": {"x0": 1237, "y0": 2805, "x1": 1320, "y1": 2800, "x2": 1313, "y2": 2864, "x3": 1237, "y3": 2864}, "line_idx": 14, "type": "H"}, {"text": "they", "polygon": {"x0": 993, "y0": 2950, "x1": 1092, "y1": 2953, "x2": 1138, "y2": 3070, "x3": 993, "y3": 3063}, "line_idx": 15, "type": "H"}, {"text": "are", "polygon": {"x0": 1229, "y0": 2970, "x1": 1305, "y1": 2975, "x2": 1323, "y2": 3016, "x3": 1229, "y3": 3014}, "line_idx": 15, "type": "H"}, {"text": "classified", "polygon": {"x0": 1436, "y0": 2926, "x1": 1676, "y1": 2928, "x2": 1703, "y2": 3002, "x3": 1443, "y3": 3019}, "line_idx": 15, "type": "H"}, {"text": "as", "polygon": {"x0": 1752, "y0": 2967, "x1": 1804, "y1": 2975, "x2": 1811, "y2": 3012, "x3": 1755, "y3": 3009}, "line_idx": 15, "type": "H"}, {"text": "type", "polygon": {"x0": 1831, "y0": 2950, "x1": 1951, "y1": 2980, "x2": 1951, "y2": 3039, "x3": 1831, "y3": 3048}, "line_idx": 15, "type": "H"}, {"text": "D.M", "polygon": {"x0": 2074, "y0": 2985, "x1": 2185, "y1": 2994, "x2": 2180, "y2": 3039, "x3": 2052, "y3": 3039}, "line_idx": 15, "type": "H"}, {"text": "M/M", "polygon": {"x0": 1315, "y0": 3100, "x1": 1426, "y1": 3115, "x2": 1426, "y2": 3169, "x3": 1325, "y3": 3169}, "line_idx": 16, "type": "H"}, {"text": "insulin", "polygon": {"x0": 1526, "y0": 3125, "x1": 1703, "y1": 3125, "x2": 1743, "y2": 3176, "x3": 1534, "y3": 3181}, "line_idx": 16, "type": "H"}, {"text": "over", "polygon": {"x0": 870, "y0": 3266, "x1": 993, "y1": 3278, "x2": 1005, "y2": 3315, "x3": 882, "y3": 3327}, "line_idx": 17, "type": "H"}, {"text": "10-15", "polygon": {"x0": 1110, "y0": 3283, "x1": 1329, "y1": 3290, "x2": 1322, "y2": 3330, "x3": 1110, "y3": 3349}, "line_idx": 17, "type": "H"}, {"text": "yr", "polygon": {"x0": 1371, "y0": 3300, "x1": 1427, "y1": 3305, "x2": 1435, "y2": 3379, "x3": 1373, "y3": 3386}, "line_idx": 17, "type": "H"}, {"text": "Insulin", "polygon": {"x0": 1673, "y0": 3288, "x1": 1833, "y1": 3288, "x2": 1874, "y2": 3349, "x3": 1670, "y3": 3364}, "line_idx": 17, "type": "H"}, {"text": "req", "polygon": {"x0": 1933, "y0": 3298, "x1": 2049, "y1": 3312, "x2": 2056, "y2": 3386, "x3": 1941, "y3": 3347}, "line_idx": 17, "type": "H"}, {"text": "start", "polygon": {"x0": 2152, "y0": 3293, "x1": 2311, "y1": 3320, "x2": 2292, "y2": 3364, "x3": 2149, "y3": 3359}, "line_idx": 17, "type": "H"}, {"text": "to", "polygon": {"x0": 2375, "y0": 3325, "x1": 2432, "y1": 3359, "x2": 2442, "y2": 3388, "x3": 2375, "y3": 3384}, "line_idx": 17, "type": "H"}, {"text": "%math%", "polygon": {"x0": 2496, "y0": 3328, "x1": 2560, "y1": 3369, "x2": 2585, "y2": 3423, "x3": 2474, "y3": 3418}, "line_idx": 17, "type": "H"}, {"text": "at", "polygon": {"x0": 1145, "y0": 3469, "x1": 1222, "y1": 3471, "x2": 1219, "y2": 3526, "x3": 1145, "y3": 3524}, "line_idx": 18, "type": "H"}, {"text": "%NA%", "polygon": {"x0": 1389, "y0": 2099, "x1": 1608, "y1": 2114, "x2": 1599, "y2": 2140, "x3": 1400, "y3": 2131}, "line_idx": 18, "type": "H"}, {"text": "%NA%", "polygon": {"x0": 1356, "y0": 2234, "x1": 1575, "y1": 2217, "x2": 1569, "y2": 2261, "x3": 1361, "y3": 2265}, "line_idx": 11, "type": "H"}, {"text": "%NA%", "polygon": {"x0": 1965, "y0": 2337, "x1": 2140, "y1": 2357, "x2": 2127, "y2": 2383, "x3": 1967, "y3": 2381}, "line_idx": 12, "type": "H"}, {"text": "point", "polygon": {"x0": 1437, "y0": 3470, "x1": 1558, "y1": 3477, "x2": 1568, "y2": 3526, "x3": 1442, "y3": 3555}, "line_idx": 12, "type": "H"}, {"text": "they", "polygon": {"x0": 1749, "y0": 3440, "x1": 1879, "y1": 3445, "x2": 1904, "y2": 3551, "x3": 1757, "y3": 3553}, "line_idx": 18, "type": "H"}, {"text": "can", "polygon": {"x0": 1975, "y0": 3492, "x1": 2088, "y1": 3504, "x2": 2093, "y2": 3541, "x3": 1978, "y3": 3531}, "line_idx": 18, "type": "H"}, {"text": "be", "polygon": {"x0": 2145, "y0": 3484, "x1": 2199, "y1": 3501, "x2": 2206, "y2": 3538, "x3": 2145, "y3": 3538}, "line_idx": 18, "type": "H"}, {"text": "M/M", "polygon": {"x0": 2302, "y0": 3497, "x1": 2400, "y1": 3528, "x2": 2400, "y2": 3585, "x3": 2299, "y3": 3570}, "line_idx": 18, "type": "H"}, {"text": "C", "polygon": {"x0": 2440, "y0": 3497, "x1": 2474, "y1": 3528, "x2": 2474, "y2": 3585, "x3": 2440, "y3": 3570}, "line_idx": 18, "type": "H"}, {"text": "oral", "polygon": {"x0": 1656, "y0": 3560, "x1": 1769, "y1": 3560, "x2": 1752, "y2": 3632, "x3": 1651, "y3": 3627}, "line_idx": 19, "type": "H"}, {"text": "drugs", "polygon": {"x0": 1806, "y0": 3558, "x1": 1943, "y1": 3600, "x2": 1911, "y2": 3698, "x3": 1784, "y3": 3637}, "line_idx": 19, "type": "H"}, {"text": "(", "polygon": {"x0": 1549, "y0": 461, "x1": 1596, "y1": 461, "x2": 1586, "y2": 569, "x3": 1547, "y3": 552}, "line_idx": 1, "type": "H"}, {"text": ")", "polygon": {"x0": 2642, "y0": 419, "x1": 2674, "y1": 424, "x2": 2672, "y2": 498, "x3": 2637, "y3": 498}, "line_idx": 1, "type": "H"}, {"text": "%math%", "polygon": {"x0": 731, "y0": 1804, "x1": 783, "y1": 1807, "x2": 803, "y2": 1834, "x3": 736, "y3": 1861}, "line_idx": 8, "type": "H"}, {"text": "(", "polygon": {"x0": 1127, "y0": 1632, "x1": 1166, "y1": 1635, "x2": 1161, "y2": 1706, "x3": 1119, "y3": 1706}, "line_idx": 7, "type": "H"}, {"text": ")", "polygon": {"x0": 1576, "y0": 1623, "x1": 1620, "y1": 1620, "x2": 1616, "y2": 1706, "x3": 1564, "y3": 1699}, "line_idx": 7, "type": "H"}, {"text": "[", "polygon": {"x0": 1237, "y0": 1912, "x1": 1284, "y1": 1917, "x2": 1277, "y2": 2016, "x3": 1240, "y3": 1989}, "line_idx": 9, "type": "H"}, {"text": "]", "polygon": {"x0": 1647, "y0": 1922, "x1": 1674, "y1": 1942, "x2": 1674, "y2": 1998, "x3": 1628, "y3": 2018}, "line_idx": 9, "type": "H"}, {"text": "(", "polygon": {"x0": 1126, "y0": 2039, "x1": 1163, "y1": 2037, "x2": 1157, "y2": 2113, "x3": 1122, "y3": 2113}, "line_idx": 10, "type": "H"}, {"text": ")", "polygon": {"x0": 1288, "y0": 2063, "x1": 1310, "y1": 2063, "x2": 1303, "y2": 2126, "x3": 1277, "y3": 2122}, "line_idx": 10, "type": "H"}, {"text": "[", "polygon": {"x0": 1921, "y0": 2304, "x1": 1966, "y1": 2316, "x2": 1948, "y2": 2397, "x3": 1912, "y3": 2390}, "line_idx": 12, "type": "H"}, {"text": "]", "polygon": {"x0": 2447, "y0": 2326, "x1": 2496, "y1": 2323, "x2": 2501, "y2": 2409, "x3": 2445, "y3": 2424}, "line_idx": 12, "type": "H"}, {"text": "%NA%", "polygon": {"x0": 757, "y0": 2798, "x1": 853, "y1": 2792, "x2": 812, "y2": 2868, "x3": 748, "y3": 2866}, "line_idx": 14, "type": "H"}, {"text": "%math%", "polygon": {"x0": 956, "y0": 2833, "x1": 993, "y1": 2836, "x2": 993, "y2": 2871, "x3": 945, "y3": 2884}, "line_idx": 14, "type": "H"}, {"text": "%NA%", "polygon": {"x0": 1156, "y0": 3094, "x1": 1201, "y1": 3097, "x2": 1196, "y2": 3168, "x3": 1169, "y3": 3153}, "line_idx": 16, "type": "H"}, {"text": "=", "polygon": {"x0": 1436, "y0": 3139, "x1": 1463, "y1": 3129, "x2": 1461, "y2": 3163, "x3": 1436, "y3": 3166}, "line_idx": 16, "type": "H"}, {"text": "%NA%", "polygon": {"x0": 1989, "y0": 2977, "x1": 2028, "y1": 2984, "x2": 2028, "y2": 3035, "x3": 1982, "y3": 3031}, "line_idx": 15, "type": "H"}, {"text": "%math%", "polygon": {"x0": 1537, "y0": 3318, "x1": 1589, "y1": 3328, "x2": 1589, "y2": 3367, "x3": 1542, "y3": 3369}, "line_idx": 17, "type": "H"}, {"text": "%math%", "polygon": {"x0": 1319, "y0": 3475, "x1": 1360, "y1": 3475, "x2": 1380, "y2": 3534, "x3": 1314, "y3": 3536}, "line_idx": 18, "type": "H"}, {"text": "%math%", "polygon": {"x0": 1344, "y0": 1760, "x1": 1412, "y1": 1773, "x2": 1393, "y2": 1849, "x3": 1358, "y3": 1851}, "line_idx": 8, "type": "H"}, {"text": "%NA%", "polygon": {"x0": 1037, "y0": 3473, "x1": 1083, "y1": 3465, "x2": 1100, "y2": 3536, "x3": 1039, "y3": 3534}, "line_idx": 18, "type": "H"}, {"text": "+", "polygon": {"x0": 849, "y0": 1018, "x1": 900, "y1": 1013, "x2": 917, "y2": 1060, "x3": 861, "y3": 1067}, "line_idx": 3, "type": "H"}, {"text": "or", "polygon": {"x0": 2206, "y0": 2341, "x1": 2251, "y1": 2341, "x2": 2232, "y2": 2383, "x3": 2193, "y3": 2386}, "line_idx": 12, "type": "H"}]